{"events": {"2026-06-29": ["절세계좌시장분석_202606", "키움증권::빗썸", "미래에셋_MAPS글로벌플랫폼_202606", "키움증권_빗썸지분검토_202606", "-::연금::202606", "미래에셋증권::해외주식::202606", "키움증권::ETF::202606", "키움증권::디지털자산::202606", "키움증권_ETF탐색서비스_202606"], "2026-06-30": ["NH투자증권, KB증권::-::202606", "글로벌블록체인_금융MOU_202606", "SK증권::연금::202606", "토스증권_AI투자정보_202606", "-::디지털자산::202606", "키움증권::채권::202606", "미래에셋_브랜드가치평가_202606", "키움증권_퇴직연금출시_202606", "SK증권_연금이전캐시백_202606", "NH투자증권::연금::202606", "토스증권::MTS플랫폼::202606", "키움증권::연금::202606", "미래에셋증권::-::202606", "NH투자증권_각자대표체제전환_202606", "트래블월렛_IPO주관_202606", "키움증권_발행어음특판_202606"], "2026-07-01": ["KB증권_마블앱고도화_202607", "KB증권::MTS플랫폼::202607", "증권사_STO거래소연계_202607", "삼성증권_-_202607", "삼성증권::디지털자산::202607", "-::디지털자산::202607", "삼성증권::빗썸", "삼성증권_두나무지분투자_202607", "-::-::202607"]}, "2026-06-30 16": {"ids": ["https://n.news.naver.com/mnews/article/018/0006318885?sid=101", "https://n.news.naver.com/mnews/article/366/0001175431?sid=101", "https://www.pinpointnews.co.kr/news/articleView.html?idxno=463468", "http://www.srtimes.kr/news/articleView.html?idxno=206409", "https://www.cbci.co.kr/news/articleView.html?idxno=585623"], "title_norms": ["연금이전혜택에자산관리까지SK증권고객유치나서", "금융사손잡는글로벌블록체인업계파트너확보전나서", "NH투자증권신재욱배광수각자대표체제로전환IBWM시너지초점", "미래에셋증권5브랜드12위800조자산운용등고객", "공포대신수익을포모깨는투자비법"], "desc_norms": ["NH투자증권은퇴직연금시장분석리포트를발간하고장기자산배분서비스를확대하고있으며키움증권도퇴직연금사업진출과함께발행어음특판등연계상품을선보이며연금고객유치에나서고있다", "출시협업및커스터디가이드발간등자산운용영역까지파트너십을확장했다해외디지털자산기업들의국내협력방식도다양해지고있다글로벌가상자산거래소OKX는한국투자증권과함께코인원지분", "NH투자증권은서비스출시3년9개월만에패밀리오피스200가문을넘어서며초고액자산가시장에서입지를넓혔다특히세무법률자문가업승계차세대교육까지아우르는가문단위자산관리플랫폼으로서비스를", "이달26일에는미래에셋증권홍콩법인이글로벌투자플랫폼MAPS를공식출시해전통자산과디지털자산을한플랫폼에서거래할수있는환경을마련했다향후미국한국중국싱가포르", "토스증권의경우역대급상승장으로포모심리가커진투자자를위한정보서비스를내놓았다해외기업실적발표실시간번역과AI기반시장분석서비스를통해투자자들이포모에휩쓸려추격매수에"]}, "2026-07-01 09": {"ids": ["https://news.dealsitetv.com/articles/172487", "https://www.youthdaily.co.kr/news/article.html?no=221928", "https://www.ceoscoredaily.com/page/view/2026063015434612599", "https://www.businesspost.co.kr/BP?command=article_view&num=440131"], "title_norms": ["키움증권빗썸도손잡나디지털자산법기대감에협업확대", "함영주하나금융지주대표이사회장", "STO스테이블코인시대앞두고증권사들거래소선점속도전", "통합앱부재에도끊김없는경험"], "desc_norms": ["증권업계의가상자산사업진출이본격화되고있다키움증권도가상자산업계2위거래소인빗썸인수를이밖에도삼성증권과한화투자증권은두나무와지분투자계약을체결했다이는최근디지털자산기본법2단계", "삼성증권은2026년5월28일삼성카드삼성SDS와함께두나무지분4를인수한다고발표했다세부적으로는국내금융회사들의해외투자유치및해외진출확대를지원하기위해마련된자리가운데하나였다당시", "1일금융투자업계등에따르면미래에셋그룹은코빗한국투자증권은코인원과손을잡았고삼성증권업계에서는원화스테이블코인과STO가제도권에편입될경우증권사와가상자산거래소간연계서비스가확대될", "명KB증권Mable이228만명을나타냈다특히Mable은전년동기대비200늘어나며주요금융플랫폼KB금융관계자도현재별도통합앱을새로출시할계획은없다는입장을밝혔다하지만경쟁사의플랫폼"]}}